odoo10_addon_l10n_nl_country_states-10.0.1.1.0-nspkg.pth
odoo/addons/l10n_nl_country_states/README.rst
odoo/addons/l10n_nl_country_states/__init__.py
odoo/addons/l10n_nl_country_states/__manifest__.py
odoo/addons/l10n_nl_country_states/__scripts__/generate_postcode_regios.py
odoo/addons/l10n_nl_country_states/data/l10n_nl_country_states.xml
odoo/addons/l10n_nl_country_states/data/res_country_state_nl_zip.xml
odoo/addons/l10n_nl_country_states/i18n/l10n_nl_country_states.pot
odoo/addons/l10n_nl_country_states/i18n/nl.po
odoo/addons/l10n_nl_country_states/i18n/nl_NL.po
odoo/addons/l10n_nl_country_states/models/__init__.py
odoo/addons/l10n_nl_country_states/models/res_country_state_nl_zip.py
odoo/addons/l10n_nl_country_states/models/res_partner.py
odoo/addons/l10n_nl_country_states/security/ir.model.access.csv
odoo/addons/l10n_nl_country_states/static/description/icon.png
odoo/addons/l10n_nl_country_states/static/description/screenshot.png
odoo/addons/l10n_nl_country_states/tests/__init__.py
odoo/addons/l10n_nl_country_states/tests/test_l10n_nl_country_states.py
odoo10_addon_l10n_nl_country_states-10.0.1.1.0.dist-info/METADATA
odoo10_addon_l10n_nl_country_states-10.0.1.1.0.dist-info/WHEEL
odoo10_addon_l10n_nl_country_states-10.0.1.1.0.dist-info/namespace_packages.txt
odoo10_addon_l10n_nl_country_states-10.0.1.1.0.dist-info/top_level.txt
odoo10_addon_l10n_nl_country_states-10.0.1.1.0.dist-info/RECORD
